simple_database_sudipOP/__init__.py
simple_database_sudipOP/simple_database.py
simple_database_sudipop-0.0.1.dist-info/METADATA
simple_database_sudipop-0.0.1.dist-info/WHEEL
simple_database_sudipop-0.0.1.dist-info/licenses/LICENCE
simple_database_sudipop-0.0.1.dist-info/RECORD
