Metadata-Version: 2.1
Name: simple_database_sudipOP
Version: 0.0.1
Summary: a simple database package for simple use
Author-email: Sudip Halder <sudipofficial8116@gmail.com>
License-File: LICENCE
Classifier: License :: OSI Approved :: MIT License
Classifier: Operating System :: OS Independent
Classifier: Programming Language :: Python :: 3
Requires-Python: >=3.2
